spo_raspi
