Metadata-Version: 1.0
Name: spo-raspi
Version: 1.2.4
Summary: SPO
Home-page: https://github.com/weidacn/SPO_raspi
Author: AW
Author-email: weidacn@qq.com
License: MIT
Keywords: raspi
Platform: any
